{
  "insights": [
    {
      "category": "Overall Sentiment",
      "insight": "The community shows predominantly positive sentiment with 68.8% positive discussions across 23,405 documents.",
      "data": {
        "total_documents": 23405,
        "positive_percentage": 68.80581072420424
      }
    },
    {
      "category": "Discussion Focus",
      "insight": "Weight loss experiences dominate discussions (72.4% of content), indicating this is the primary reason people use semaglutide in these communities.",
      "data": {
        "dominant_topic": 0,
        "dominant_topic_name": "Alternative Medications",
        "percentage": 72.4161503952147
      }
    },
    {
      "category": "Community Dynamics",
      "insight": "Community support discussions are overwhelmingly positive (67.2%), demonstrating strong peer support and helpful information sharing.",
      "data": {
        "support_positive_percentage": 67.1875
      }
    },
    {
      "category": "Side Effects",
      "insight": "Despite discussions about side effects, 69.1% remain positive, suggesting benefits outweigh adverse effects for most users.",
      "data": {
        "side_effects_positive_percentage": 69.0909090909091
      }
    },
    {
      "category": "Access & Affordability",
      "insight": "Insurance/access discussions are more positive than expected (49.1%), likely due to community sharing solutions and support for obtaining medication.",
      "data": {
        "insurance_positive_percentage": 49.130434782608695
      }
    },
    {
      "category": "Temporal Trends",
      "insight": "Sentiment remains consistently positive across years (0.348 average), indicating sustained satisfaction over time.",
      "data": {
        "mean_sentiment_across_years": 0.3477167635906842,
        "yearly_sentiment": {
          "2019": 0.4152857142857143,
          "2020": 0.387765606361829,
          "2021": 0.38509990689013035,
          "2022": 0.3301433962264151,
          "2023": 0.26540351027397263,
          "2024": 0.32001017909356727,
          "2025": 0.3303090320031608
        }
      }
    },
    {
      "category": "Topic-Sentiment Relationship",
      "insight": "Sentiment varies significantly by topic, with community support (0.52) being most positive and alternative medications (-0.04) being slightly negative.",
      "data": {
        "topic_sentiment_ranking": {
          "Weight Loss Experiences": 0.5072007532956685,
          "Alternative Medications": 0.3364340787067084,
          "Diet & Side Effects": 0.32923616161616165,
          "Community Support": 0.30755454545454547,
          "Insurance & Access": 0.10603445652173912
        }
      }
    }
  ]
}